cnnutils/__init__.py
cnnutilstp-3.0.1.dist-info/LICENCE
cnnutilstp-3.0.1.dist-info/METADATA
cnnutilstp-3.0.1.dist-info/WHEEL
cnnutilstp-3.0.1.dist-info/top_level.txt
cnnutilstp-3.0.1.dist-info/RECORD
