Metadata-Version: 2.1
Name: cnnutilstp
Version: 3.0.1
Summary: file needed in the tp
Home-page: https://github.com/Tragadoss/cnnutils
Author: tragadoss
Author-email: heitam159@gmail.com
License: UNKNOWN
Project-URL: Bug Tracker, https://github.com/Tragadoss/cnnutils
Platform: UNKNOWN
Classifier: Programming Language :: Python :: 3
Classifier: License :: OSI Approved :: MIT License
Classifier: Operating System :: OS Independent
Requires-Python: >=3.6
License-File: LICENCE
